[{"name":"Simulation","roi":{"DRAM":[{"AVG DBUS CONGESTED CYCLE":2.568532267275842,"REFRESHES ISSUED":117,"RQ ROW_BUFFER_HIT":105,"RQ ROW_BUFFER_MISS":9772,"WQ ROW_BUFFER_HIT":0,"WQ ROW_BUFFER_MISS":0}],"LLC":{"LOAD":{"hit":[19],"miss":[3490],"mshr_merge":[0]},"PREFETCH":{"hit":[19],"miss":[3450],"mshr_merge":[0]},"RFO":{"hit":[0],"miss":[695],"mshr_merge":[0]},"TRANSLATION":{"hit":[5],"miss":[2243],"mshr_merge":[0]},"WRITE":{"hit":[333],"miss":[0],"mshr_merge":[0]},"miss latency":193.1255444928438,"prefetch issued":0,"prefetch requested":0,"useful prefetch":0,"useless prefetch":0},"cores":[{"Avg ROB occupancy at mispredict":33.22291481151677,"cycles":1402779,"instructions":200004,"mispredict":{"BRANCH_CONDITIONAL":2888,"BRANCH_DIRECT_CALL":47,"BRANCH_DIRECT_JUMP":20,"BRANCH_INDIRECT":87,"BRANCH_INDIRECT_CALL":105,"BRANCH_RETURN":222}}],"cpu0_DTLB":{"LOAD":{"hit":[65744],"miss":[6101],"mshr_merge":[2023]},"PREFETCH":{"hit":[0],"miss":[0],"mshr_merge":[0]},"RFO":{"hit":[0],"miss":[0],"mshr_merge":[0]},"TRANSLATION":{"hit":[0],"miss":[0],"mshr_merge":[0]},"WRITE":{"hit":[0],"miss":[0],"mshr_merge":[0]},"miss latency":249.1094247246022,"prefetch issued":0,"prefetch requested":0,"useful prefetch":0,"useless prefetch":0},"cpu0_ITLB":{"LOAD":{"hit":[23319],"miss":[748],"mshr_merge":[408]},"PREFETCH":{"hit":[0],"miss":[0],"mshr_merge":[0]},"RFO":{"hit":[0],"miss":[0],"mshr_merge":[0]},"TRANSLATION":{"hit":[0],"miss":[0],"mshr_merge":[0]},"WRITE":{"hit":[0],"miss":[0],"mshr_merge":[0]},"miss latency":55.97093023255814,"prefetch issued":0,"prefetch requested":0,"useful prefetch":0,"useless prefetch":0},"cpu0_L1D":{"LOAD":{"hit":[30119],"miss":[7818],"mshr_merge":[2905]},"PREFETCH":{"hit":[0],"miss":[0],"mshr_merge":[0]},"RFO":{"hit":[0],"miss":[0],"mshr_merge":[0]},"TRANSLATION":{"hit":[209],"miss":[2320],"mshr_merge":[18]},"WRITE":{"hit":[33040],"miss":[4018],"mshr_merge":[3212]},"miss latency":177.51352699164693,"prefetch issued":0,"prefetch requested":0,"useful prefetch":0,"useless prefetch":0},"cpu0_L1I":{"LOAD":{"hit":[27474],"miss":[142],"mshr_merge":[10]},"PREFETCH":{"hit":[0],"miss":[0],"mshr_merge":[0]},"RFO":{"hit":[0],"miss":[0],"mshr_merge":[0]},"TRANSLATION":{"hit":[0],"miss":[0],"mshr_merge":[0]},"WRITE":{"hit":[0],"miss":[0],"mshr_merge":[0]},"miss latency":153.24242424242425,"prefetch issued":0,"prefetch requested":0,"useful prefetch":0,"useless prefetch":0},"cpu0_L2C":{"LOAD":{"hit":[1360],"miss":[3685],"mshr_merge":[176]},"PREFETCH":{"hit":[802],"miss":[4243],"mshr_merge":[774]},"RFO":{"hit":[111],"miss":[695],"mshr_merge":[0]},"TRANSLATION":{"hit":[54],"miss":[2248],"mshr_merge":[0]},"WRITE":{"hit":[1577],"miss":[1],"mshr_merge":[0]},"miss latency":206.93634032282395,"prefetch issued":5045,"prefetch requested":5045,"useful prefetch":1287,"useless prefetch":534},"cpu0_STLB":{"LOAD":{"hit":[3199],"miss":[1218],"mshr_merge":[0]},"PREFETCH":{"hit":[0],"miss":[0],"mshr_merge":[0]},"RFO":{"hit":[0],"miss":[0],"mshr_merge":[0]},"TRANSLATION":{"hit":[0],"miss":[0],"mshr_merge":[0]},"WRITE":{"hit":[0],"miss":[0],"mshr_merge":[0]},"miss latency":824.0121951219512,"prefetch issued":0,"prefetch requested":0,"useful prefetch":0,"useless prefetch":0}},"sim":{"DRAM":[{"AVG DBUS CONGESTED CYCLE":2.568532267275842,"REFRESHES ISSUED":117,"RQ ROW_BUFFER_HIT":105,"RQ ROW_BUFFER_MISS":9772,"WQ ROW_BUFFER_HIT":0,"WQ ROW_BUFFER_MISS":0}],"LLC":{"LOAD":{"hit":[19],"miss":[3490],"mshr_merge":[0]},"PREFETCH":{"hit":[19],"miss":[3450],"mshr_merge":[0]},"RFO":{"hit":[0],"miss":[695],"mshr_merge":[0]},"TRANSLATION":{"hit":[5],"miss":[2243],"mshr_merge":[0]},"WRITE":{"hit":[333],"miss":[0],"mshr_merge":[0]},"miss latency":193.1255444928438,"prefetch issued":0,"prefetch requested":0,"useful prefetch":0,"useless prefetch":0},"cores":[{"Avg ROB occupancy at mispredict":33.22291481151677,"cycles":1402779,"instructions":200004,"mispredict":{"BRANCH_CONDITIONAL":2888,"BRANCH_DIRECT_CALL":47,"BRANCH_DIRECT_JUMP":20,"BRANCH_INDIRECT":87,"BRANCH_INDIRECT_CALL":105,"BRANCH_RETURN":222}}],"cpu0_DTLB":{"LOAD":{"hit":[65744],"miss":[6101],"mshr_merge":[2023]},"PREFETCH":{"hit":[0],"miss":[0],"mshr_merge":[0]},"RFO":{"hit":[0],"miss":[0],"mshr_merge":[0]},"TRANSLATION":{"hit":[0],"miss":[0],"mshr_merge":[0]},"WRITE":{"hit":[0],"miss":[0],"mshr_merge":[0]},"miss latency":249.1094247246022,"prefetch issued":0,"prefetch requested":0,"useful prefetch":0,"useless prefetch":0},"cpu0_ITLB":{"LOAD":{"hit":[23319],"miss":[748],"mshr_merge":[408]},"PREFETCH":{"hit":[0],"miss":[0],"mshr_merge":[0]},"RFO":{"hit":[0],"miss":[0],"mshr_merge":[0]},"TRANSLATION":{"hit":[0],"miss":[0],"mshr_merge":[0]},"WRITE":{"hit":[0],"miss":[0],"mshr_merge":[0]},"miss latency":55.97093023255814,"prefetch issued":0,"prefetch requested":0,"useful prefetch":0,"useless prefetch":0},"cpu0_L1D":{"LOAD":{"hit":[30119],"miss":[7818],"mshr_merge":[2905]},"PREFETCH":{"hit":[0],"miss":[0],"mshr_merge":[0]},"RFO":{"hit":[0],"miss":[0],"mshr_merge":[0]},"TRANSLATION":{"hit":[209],"miss":[2320],"mshr_merge":[18]},"WRITE":{"hit":[33040],"miss":[4018],"mshr_merge":[3212]},"miss latency":177.51352699164693,"prefetch issued":0,"prefetch requested":0,"useful prefetch":0,"useless prefetch":0},"cpu0_L1I":{"LOAD":{"hit":[27474],"miss":[142],"mshr_merge":[10]},"PREFETCH":{"hit":[0],"miss":[0],"mshr_merge":[0]},"RFO":{"hit":[0],"miss":[0],"mshr_merge":[0]},"TRANSLATION":{"hit":[0],"miss":[0],"mshr_merge":[0]},"WRITE":{"hit":[0],"miss":[0],"mshr_merge":[0]},"miss latency":153.24242424242425,"prefetch issued":0,"prefetch requested":0,"useful prefetch":0,"useless prefetch":0},"cpu0_L2C":{"LOAD":{"hit":[1360],"miss":[3685],"mshr_merge":[176]},"PREFETCH":{"hit":[802],"miss":[4243],"mshr_merge":[774]},"RFO":{"hit":[111],"miss":[695],"mshr_merge":[0]},"TRANSLATION":{"hit":[54],"miss":[2248],"mshr_merge":[0]},"WRITE":{"hit":[1577],"miss":[1],"mshr_merge":[0]},"miss latency":206.93634032282395,"prefetch issued":5045,"prefetch requested":5045,"useful prefetch":1287,"useless prefetch":534},"cpu0_STLB":{"LOAD":{"hit":[3199],"miss":[1218],"mshr_merge":[0]},"PREFETCH":{"hit":[0],"miss":[0],"mshr_merge":[0]},"RFO":{"hit":[0],"miss":[0],"mshr_merge":[0]},"TRANSLATION":{"hit":[0],"miss":[0],"mshr_merge":[0]},"WRITE":{"hit":[0],"miss":[0],"mshr_merge":[0]},"miss latency":824.0121951219512,"prefetch issued":0,"prefetch requested":0,"useful prefetch":0,"useless prefetch":0}},"traces":["/users/lijrjyan/ChampSim_checkpoint/471.omnetpp-188B.champsimtrace.xz"]}]