[{"name":"Simulation","roi":{"DRAM":[{"AVG DBUS CONGESTED CYCLE":2.8174812411275605,"REFRESHES ISSUED":134,"RQ ROW_BUFFER_HIT":50,"RQ ROW_BUFFER_MISS":7989,"WQ ROW_BUFFER_HIT":0,"WQ ROW_BUFFER_MISS":0}],"LLC":{"LOAD":{"hit":[193],"miss":[3329],"mshr_merge":[40]},"PREFETCH":{"hit":[54],"miss":[1723],"mshr_merge":[30]},"RFO":{"hit":[22],"miss":[407],"mshr_merge":[3]},"TRANSLATION":{"hit":[9],"miss":[2651],"mshr_merge":[0]},"WRITE":{"hit":[190],"miss":[0],"mshr_merge":[0]},"miss latency":184.35780247300048,"prefetch issued":0,"prefetch requested":0,"useful prefetch":0,"useless prefetch":0},"cores":[{"Avg ROB occupancy at mispredict":41.430834213305175,"cycles":1618053,"instructions":200002,"mispredict":{"BRANCH_CONDITIONAL":1726,"BRANCH_DIRECT_CALL":111,"BRANCH_DIRECT_JUMP":203,"BRANCH_INDIRECT":138,"BRANCH_INDIRECT_CALL":369,"BRANCH_RETURN":294}}],"cpu0_DTLB":{"LOAD":{"hit":[67588],"miss":[5234],"mshr_merge":[979]},"PREFETCH":{"hit":[0],"miss":[0],"mshr_merge":[0]},"RFO":{"hit":[0],"miss":[0],"mshr_merge":[0]},"TRANSLATION":{"hit":[0],"miss":[0],"mshr_merge":[0]},"WRITE":{"hit":[0],"miss":[0],"mshr_merge":[0]},"miss latency":270.15922968529827,"prefetch issued":0,"prefetch requested":0,"useful prefetch":0,"useless prefetch":0},"cpu0_ITLB":{"LOAD":{"hit":[41954],"miss":[752],"mshr_merge":[330]},"PREFETCH":{"hit":[0],"miss":[0],"mshr_merge":[0]},"RFO":{"hit":[0],"miss":[0],"mshr_merge":[0]},"TRANSLATION":{"hit":[0],"miss":[0],"mshr_merge":[0]},"WRITE":{"hit":[0],"miss":[0],"mshr_merge":[0]},"miss latency":103.27725118483413,"prefetch issued":0,"prefetch requested":0,"useful prefetch":0,"useless prefetch":0},"cpu0_L1D":{"LOAD":{"hit":[36245],"miss":[4961],"mshr_merge":[1179]},"PREFETCH":{"hit":[37],"miss":[843],"mshr_merge":[19]},"RFO":{"hit":[0],"miss":[0],"mshr_merge":[0]},"TRANSLATION":{"hit":[214],"miss":[3127],"mshr_merge":[9]},"WRITE":{"hit":[34233],"miss":[1648],"mshr_merge":[1178]},"miss latency":173.08747461069737,"prefetch issued":880,"prefetch requested":973,"useful prefetch":152,"useless prefetch":627},"cpu0_L1I":{"LOAD":{"hit":[28719],"miss":[542],"mshr_merge":[66]},"PREFETCH":{"hit":[22710],"miss":[92],"mshr_merge":[27]},"RFO":{"hit":[0],"miss":[0],"mshr_merge":[0]},"TRANSLATION":{"hit":[0],"miss":[0],"mshr_merge":[0]},"WRITE":{"hit":[0],"miss":[0],"mshr_merge":[0]},"miss latency":157.24430641821945,"prefetch issued":22802,"prefetch requested":24481,"useful prefetch":45,"useless prefetch":14},"cpu0_L2C":{"LOAD":{"hit":[737],"miss":[3522],"mshr_merge":[0]},"PREFETCH":{"hit":[248],"miss":[2297],"mshr_merge":[520]},"RFO":{"hit":[41],"miss":[429],"mshr_merge":[0]},"TRANSLATION":{"hit":[458],"miss":[2660],"mshr_merge":[0]},"WRITE":{"hit":[1751],"miss":[22],"mshr_merge":[0]},"miss latency":193.417872212176,"prefetch issued":1656,"prefetch requested":1656,"useful prefetch":0,"useless prefetch":1},"cpu0_STLB":{"LOAD":{"hit":[3268],"miss":[1409],"mshr_merge":[0]},"PREFETCH":{"hit":[0],"miss":[0],"mshr_merge":[0]},"RFO":{"hit":[0],"miss":[0],"mshr_merge":[0]},"TRANSLATION":{"hit":[0],"miss":[0],"mshr_merge":[0]},"WRITE":{"hit":[0],"miss":[0],"mshr_merge":[0]},"miss latency":827.9773371104816,"prefetch issued":0,"prefetch requested":0,"useful prefetch":0,"useless prefetch":0}},"sim":{"DRAM":[{"AVG DBUS CONGESTED CYCLE":2.8174812411275605,"REFRESHES ISSUED":134,"RQ ROW_BUFFER_HIT":50,"RQ ROW_BUFFER_MISS":7989,"WQ ROW_BUFFER_HIT":0,"WQ ROW_BUFFER_MISS":0}],"LLC":{"LOAD":{"hit":[193],"miss":[3329],"mshr_merge":[40]},"PREFETCH":{"hit":[54],"miss":[1723],"mshr_merge":[30]},"RFO":{"hit":[22],"miss":[407],"mshr_merge":[3]},"TRANSLATION":{"hit":[9],"miss":[2651],"mshr_merge":[0]},"WRITE":{"hit":[190],"miss":[0],"mshr_merge":[0]},"miss latency":184.35780247300048,"prefetch issued":0,"prefetch requested":0,"useful prefetch":0,"useless prefetch":0},"cores":[{"Avg ROB occupancy at mispredict":41.430834213305175,"cycles":1618053,"instructions":200002,"mispredict":{"BRANCH_CONDITIONAL":1726,"BRANCH_DIRECT_CALL":111,"BRANCH_DIRECT_JUMP":203,"BRANCH_INDIRECT":138,"BRANCH_INDIRECT_CALL":369,"BRANCH_RETURN":294}}],"cpu0_DTLB":{"LOAD":{"hit":[67588],"miss":[5234],"mshr_merge":[979]},"PREFETCH":{"hit":[0],"miss":[0],"mshr_merge":[0]},"RFO":{"hit":[0],"miss":[0],"mshr_merge":[0]},"TRANSLATION":{"hit":[0],"miss":[0],"mshr_merge":[0]},"WRITE":{"hit":[0],"miss":[0],"mshr_merge":[0]},"miss latency":270.15922968529827,"prefetch issued":0,"prefetch requested":0,"useful prefetch":0,"useless prefetch":0},"cpu0_ITLB":{"LOAD":{"hit":[41954],"miss":[752],"mshr_merge":[330]},"PREFETCH":{"hit":[0],"miss":[0],"mshr_merge":[0]},"RFO":{"hit":[0],"miss":[0],"mshr_merge":[0]},"TRANSLATION":{"hit":[0],"miss":[0],"mshr_merge":[0]},"WRITE":{"hit":[0],"miss":[0],"mshr_merge":[0]},"miss latency":103.27725118483413,"prefetch issued":0,"prefetch requested":0,"useful prefetch":0,"useless prefetch":0},"cpu0_L1D":{"LOAD":{"hit":[36245],"miss":[4961],"mshr_merge":[1179]},"PREFETCH":{"hit":[37],"miss":[843],"mshr_merge":[19]},"RFO":{"hit":[0],"miss":[0],"mshr_merge":[0]},"TRANSLATION":{"hit":[214],"miss":[3127],"mshr_merge":[9]},"WRITE":{"hit":[34233],"miss":[1648],"mshr_merge":[1178]},"miss latency":173.08747461069737,"prefetch issued":880,"prefetch requested":973,"useful prefetch":152,"useless prefetch":627},"cpu0_L1I":{"LOAD":{"hit":[28719],"miss":[542],"mshr_merge":[66]},"PREFETCH":{"hit":[22710],"miss":[92],"mshr_merge":[27]},"RFO":{"hit":[0],"miss":[0],"mshr_merge":[0]},"TRANSLATION":{"hit":[0],"miss":[0],"mshr_merge":[0]},"WRITE":{"hit":[0],"miss":[0],"mshr_merge":[0]},"miss latency":157.24430641821945,"prefetch issued":22802,"prefetch requested":24481,"useful prefetch":45,"useless prefetch":14},"cpu0_L2C":{"LOAD":{"hit":[737],"miss":[3522],"mshr_merge":[0]},"PREFETCH":{"hit":[248],"miss":[2297],"mshr_merge":[520]},"RFO":{"hit":[41],"miss":[429],"mshr_merge":[0]},"TRANSLATION":{"hit":[458],"miss":[2660],"mshr_merge":[0]},"WRITE":{"hit":[1751],"miss":[22],"mshr_merge":[0]},"miss latency":193.417872212176,"prefetch issued":1656,"prefetch requested":1656,"useful prefetch":0,"useless prefetch":1},"cpu0_STLB":{"LOAD":{"hit":[3268],"miss":[1409],"mshr_merge":[0]},"PREFETCH":{"hit":[0],"miss":[0],"mshr_merge":[0]},"RFO":{"hit":[0],"miss":[0],"mshr_merge":[0]},"TRANSLATION":{"hit":[0],"miss":[0],"mshr_merge":[0]},"WRITE":{"hit":[0],"miss":[0],"mshr_merge":[0]},"miss latency":827.9773371104816,"prefetch issued":0,"prefetch requested":0,"useful prefetch":0,"useless prefetch":0}},"traces":["/users/lijrjyan/ChampSim_checkpoint/traces/620.omnetpp_s-141B.champsimtrace.xz"]}]