[{"name":"Simulation","roi":{"DRAM":[{"AVG DBUS CONGESTED CYCLE":2.9541394709721747,"REFRESHES ISSUED":11,"RQ ROW_BUFFER_HIT":9,"RQ ROW_BUFFER_MISS":6490,"WQ ROW_BUFFER_HIT":0,"WQ ROW_BUFFER_MISS":0}],"LLC":{"LOAD":{"hit":[720],"miss":[100],"mshr_merge":[31]},"PREFETCH":{"hit":[5790],"miss":[4409],"mshr_merge":[3080]},"RFO":{"hit":[22],"miss":[4941],"mshr_merge":[0]},"TRANSLATION":{"hit":[0],"miss":[167],"mshr_merge":[0]},"WRITE":{"hit":[136],"miss":[0],"mshr_merge":[0]},"miss latency":259.19361661218994,"prefetch issued":0,"prefetch requested":0,"useful prefetch":0,"useless prefetch":0},"cores":[{"Avg ROB occupancy at mispredict":239.55555555555554,"cycles":135801,"instructions":200002,"mispredict":{"BRANCH_CONDITIONAL":9,"BRANCH_DIRECT_CALL":0,"BRANCH_DIRECT_JUMP":0,"BRANCH_INDIRECT":0,"BRANCH_INDIRECT_CALL":0,"BRANCH_RETURN":0}}],"cpu0_DTLB":{"LOAD":{"hit":[31386],"miss":[706],"mshr_merge":[592]},"PREFETCH":{"hit":[0],"miss":[0],"mshr_merge":[0]},"RFO":{"hit":[0],"miss":[0],"mshr_merge":[0]},"TRANSLATION":{"hit":[0],"miss":[0],"mshr_merge":[0]},"WRITE":{"hit":[0],"miss":[0],"mshr_merge":[0]},"miss latency":895.591304347826,"prefetch issued":0,"prefetch requested":0,"useful prefetch":0,"useless prefetch":0},"cpu0_ITLB":{"LOAD":{"hit":[29254],"miss":[0],"mshr_merge":[0]},"PREFETCH":{"hit":[0],"miss":[0],"mshr_merge":[0]},"RFO":{"hit":[0],"miss":[0],"mshr_merge":[0]},"TRANSLATION":{"hit":[0],"miss":[0],"mshr_merge":[0]},"WRITE":{"hit":[0],"miss":[0],"mshr_merge":[0]},"miss latency":null,"prefetch issued":0,"prefetch requested":0,"useful prefetch":0,"useless prefetch":0},"cpu0_L1D":{"LOAD":{"hit":[11314],"miss":[1705],"mshr_merge":[315]},"PREFETCH":{"hit":[0],"miss":[0],"mshr_merge":[0]},"RFO":{"hit":[0],"miss":[0],"mshr_merge":[0]},"TRANSLATION":{"hit":[31],"miss":[206],"mshr_merge":[13]},"WRITE":{"hit":[11812],"miss":[8111],"mshr_merge":[317]},"miss latency":163.51526147278548,"prefetch issued":0,"prefetch requested":0,"useful prefetch":3,"useless prefetch":0},"cpu0_L1I":{"LOAD":{"hit":[37768],"miss":[4],"mshr_merge":[2]},"PREFETCH":{"hit":[0],"miss":[0],"mshr_merge":[0]},"RFO":{"hit":[0],"miss":[0],"mshr_merge":[0]},"TRANSLATION":{"hit":[0],"miss":[0],"mshr_merge":[0]},"WRITE":{"hit":[0],"miss":[0],"mshr_merge":[0]},"miss latency":280.0,"prefetch issued":0,"prefetch requested":0,"useful prefetch":0,"useless prefetch":0},"cpu0_L2C":{"LOAD":{"hit":[357],"miss":[1035],"mshr_merge":[215]},"PREFETCH":{"hit":[27],"miss":[10572],"mshr_merge":[373]},"RFO":{"hit":[2831],"miss":[4963],"mshr_merge":[0]},"TRANSLATION":{"hit":[26],"miss":[167],"mshr_merge":[0]},"WRITE":{"hit":[7224],"miss":[2],"mshr_merge":[0]},"miss latency":234.55016233766233,"prefetch issued":10599,"prefetch requested":12066,"useful prefetch":572,"useless prefetch":0},"cpu0_STLB":{"LOAD":{"hit":[0],"miss":[114],"mshr_merge":[0]},"PREFETCH":{"hit":[0],"miss":[0],"mshr_merge":[0]},"RFO":{"hit":[0],"miss":[0],"mshr_merge":[0]},"TRANSLATION":{"hit":[0],"miss":[0],"mshr_merge":[0]},"WRITE":{"hit":[0],"miss":[0],"mshr_merge":[0]},"miss latency":889.6260869565217,"prefetch issued":0,"prefetch requested":0,"useful prefetch":0,"useless prefetch":0}},"sim":{"DRAM":[{"AVG DBUS CONGESTED CYCLE":2.9541394709721747,"REFRESHES ISSUED":11,"RQ ROW_BUFFER_HIT":9,"RQ ROW_BUFFER_MISS":6490,"WQ ROW_BUFFER_HIT":0,"WQ ROW_BUFFER_MISS":0}],"LLC":{"LOAD":{"hit":[720],"miss":[100],"mshr_merge":[31]},"PREFETCH":{"hit":[5790],"miss":[4409],"mshr_merge":[3080]},"RFO":{"hit":[22],"miss":[4941],"mshr_merge":[0]},"TRANSLATION":{"hit":[0],"miss":[167],"mshr_merge":[0]},"WRITE":{"hit":[136],"miss":[0],"mshr_merge":[0]},"miss latency":259.19361661218994,"prefetch issued":0,"prefetch requested":0,"useful prefetch":0,"useless prefetch":0},"cores":[{"Avg ROB occupancy at mispredict":239.55555555555554,"cycles":135801,"instructions":200002,"mispredict":{"BRANCH_CONDITIONAL":9,"BRANCH_DIRECT_CALL":0,"BRANCH_DIRECT_JUMP":0,"BRANCH_INDIRECT":0,"BRANCH_INDIRECT_CALL":0,"BRANCH_RETURN":0}}],"cpu0_DTLB":{"LOAD":{"hit":[31386],"miss":[706],"mshr_merge":[592]},"PREFETCH":{"hit":[0],"miss":[0],"mshr_merge":[0]},"RFO":{"hit":[0],"miss":[0],"mshr_merge":[0]},"TRANSLATION":{"hit":[0],"miss":[0],"mshr_merge":[0]},"WRITE":{"hit":[0],"miss":[0],"mshr_merge":[0]},"miss latency":895.591304347826,"prefetch issued":0,"prefetch requested":0,"useful prefetch":0,"useless prefetch":0},"cpu0_ITLB":{"LOAD":{"hit":[29254],"miss":[0],"mshr_merge":[0]},"PREFETCH":{"hit":[0],"miss":[0],"mshr_merge":[0]},"RFO":{"hit":[0],"miss":[0],"mshr_merge":[0]},"TRANSLATION":{"hit":[0],"miss":[0],"mshr_merge":[0]},"WRITE":{"hit":[0],"miss":[0],"mshr_merge":[0]},"miss latency":null,"prefetch issued":0,"prefetch requested":0,"useful prefetch":0,"useless prefetch":0},"cpu0_L1D":{"LOAD":{"hit":[11314],"miss":[1705],"mshr_merge":[315]},"PREFETCH":{"hit":[0],"miss":[0],"mshr_merge":[0]},"RFO":{"hit":[0],"miss":[0],"mshr_merge":[0]},"TRANSLATION":{"hit":[31],"miss":[206],"mshr_merge":[13]},"WRITE":{"hit":[11812],"miss":[8111],"mshr_merge":[317]},"miss latency":163.51526147278548,"prefetch issued":0,"prefetch requested":0,"useful prefetch":3,"useless prefetch":0},"cpu0_L1I":{"LOAD":{"hit":[37768],"miss":[4],"mshr_merge":[2]},"PREFETCH":{"hit":[0],"miss":[0],"mshr_merge":[0]},"RFO":{"hit":[0],"miss":[0],"mshr_merge":[0]},"TRANSLATION":{"hit":[0],"miss":[0],"mshr_merge":[0]},"WRITE":{"hit":[0],"miss":[0],"mshr_merge":[0]},"miss latency":280.0,"prefetch issued":0,"prefetch requested":0,"useful prefetch":0,"useless prefetch":0},"cpu0_L2C":{"LOAD":{"hit":[357],"miss":[1035],"mshr_merge":[215]},"PREFETCH":{"hit":[27],"miss":[10572],"mshr_merge":[373]},"RFO":{"hit":[2831],"miss":[4963],"mshr_merge":[0]},"TRANSLATION":{"hit":[26],"miss":[167],"mshr_merge":[0]},"WRITE":{"hit":[7224],"miss":[2],"mshr_merge":[0]},"miss latency":234.55016233766233,"prefetch issued":10599,"prefetch requested":12066,"useful prefetch":572,"useless prefetch":0},"cpu0_STLB":{"LOAD":{"hit":[0],"miss":[114],"mshr_merge":[0]},"PREFETCH":{"hit":[0],"miss":[0],"mshr_merge":[0]},"RFO":{"hit":[0],"miss":[0],"mshr_merge":[0]},"TRANSLATION":{"hit":[0],"miss":[0],"mshr_merge":[0]},"WRITE":{"hit":[0],"miss":[0],"mshr_merge":[0]},"miss latency":889.6260869565217,"prefetch issued":0,"prefetch requested":0,"useful prefetch":0,"useless prefetch":0}},"traces":["/users/lijrjyan/ChampSim_checkpoint/traces/470.lbm-1274B.champsimtrace.xz"]}]