[{"name":"Simulation","roi":{"DRAM":[{"AVG DBUS CONGESTED CYCLE":2.910246066962485,"REFRESHES ISSUED":30,"RQ ROW_BUFFER_HIT":1272,"RQ ROW_BUFFER_MISS":5465,"WQ ROW_BUFFER_HIT":0,"WQ ROW_BUFFER_MISS":0}],"LLC":{"LOAD":{"hit":[550],"miss":[1341],"mshr_merge":[5]},"PREFETCH":{"hit":[2276],"miss":[6718],"mshr_merge":[2068]},"RFO":{"hit":[0],"miss":[0],"mshr_merge":[0]},"TRANSLATION":{"hit":[0],"miss":[758],"mshr_merge":[0]},"WRITE":{"hit":[0],"miss":[0],"mshr_merge":[0]},"miss latency":220.01524535493093,"prefetch issued":0,"prefetch requested":0,"useful prefetch":0,"useless prefetch":0},"cores":[{"Avg ROB occupancy at mispredict":180.0,"cycles":365727,"instructions":200004,"mispredict":{"BRANCH_CONDITIONAL":4,"BRANCH_DIRECT_CALL":0,"BRANCH_DIRECT_JUMP":1,"BRANCH_INDIRECT":0,"BRANCH_INDIRECT_CALL":0,"BRANCH_RETURN":0}}],"cpu0_DTLB":{"LOAD":{"hit":[103205],"miss":[1846],"mshr_merge":[354]},"PREFETCH":{"hit":[0],"miss":[0],"mshr_merge":[0]},"RFO":{"hit":[0],"miss":[0],"mshr_merge":[0]},"TRANSLATION":{"hit":[0],"miss":[0],"mshr_merge":[0]},"WRITE":{"hit":[0],"miss":[0],"mshr_merge":[0]},"miss latency":321.9101876675603,"prefetch issued":0,"prefetch requested":0,"useful prefetch":0,"useless prefetch":0},"cpu0_ITLB":{"LOAD":{"hit":[55632],"miss":[0],"mshr_merge":[0]},"PREFETCH":{"hit":[0],"miss":[0],"mshr_merge":[0]},"RFO":{"hit":[0],"miss":[0],"mshr_merge":[0]},"TRANSLATION":{"hit":[0],"miss":[0],"mshr_merge":[0]},"WRITE":{"hit":[0],"miss":[0],"mshr_merge":[0]},"miss latency":null,"prefetch issued":0,"prefetch requested":0,"useful prefetch":0,"useless prefetch":0},"cpu0_L1D":{"LOAD":{"hit":[91873],"miss":[3013],"mshr_merge":[847]},"PREFETCH":{"hit":[212],"miss":[2650],"mshr_merge":[0]},"RFO":{"hit":[0],"miss":[0],"mshr_merge":[0]},"TRANSLATION":{"hit":[536],"miss":[812],"mshr_merge":[0]},"WRITE":{"hit":[12818],"miss":[2],"mshr_merge":[2]},"miss latency":177.88329979879276,"prefetch issued":2862,"prefetch requested":4276,"useful prefetch":1695,"useless prefetch":882},"cpu0_L1I":{"LOAD":{"hit":[62482],"miss":[15],"mshr_merge":[6]},"PREFETCH":{"hit":[0],"miss":[0],"mshr_merge":[0]},"RFO":{"hit":[0],"miss":[0],"mshr_merge":[0]},"TRANSLATION":{"hit":[0],"miss":[0],"mshr_merge":[0]},"WRITE":{"hit":[0],"miss":[0],"mshr_merge":[0]},"miss latency":172.66666666666666,"prefetch issued":0,"prefetch requested":0,"useful prefetch":0,"useless prefetch":0},"cpu0_L2C":{"LOAD":{"hit":[281],"miss":[1894],"mshr_merge":[3]},"PREFETCH":{"hit":[394],"miss":[12133],"mshr_merge":[3139]},"RFO":{"hit":[0],"miss":[0],"mshr_merge":[0]},"TRANSLATION":{"hit":[54],"miss":[758],"mshr_merge":[0]},"WRITE":{"hit":[1646],"miss":[3],"mshr_merge":[0]},"miss latency":189.90885122410546,"prefetch issued":9879,"prefetch requested":10809,"useful prefetch":179,"useless prefetch":2},"cpu0_STLB":{"LOAD":{"hit":[818],"miss":[674],"mshr_merge":[0]},"PREFETCH":{"hit":[0],"miss":[0],"mshr_merge":[0]},"RFO":{"hit":[0],"miss":[0],"mshr_merge":[0]},"TRANSLATION":{"hit":[0],"miss":[0],"mshr_merge":[0]},"WRITE":{"hit":[0],"miss":[0],"mshr_merge":[0]},"miss latency":700.526706231454,"prefetch issued":0,"prefetch requested":0,"useful prefetch":0,"useless prefetch":0}},"sim":{"DRAM":[{"AVG DBUS CONGESTED CYCLE":2.910246066962485,"REFRESHES ISSUED":30,"RQ ROW_BUFFER_HIT":1272,"RQ ROW_BUFFER_MISS":5465,"WQ ROW_BUFFER_HIT":0,"WQ ROW_BUFFER_MISS":0}],"LLC":{"LOAD":{"hit":[550],"miss":[1341],"mshr_merge":[5]},"PREFETCH":{"hit":[2276],"miss":[6718],"mshr_merge":[2068]},"RFO":{"hit":[0],"miss":[0],"mshr_merge":[0]},"TRANSLATION":{"hit":[0],"miss":[758],"mshr_merge":[0]},"WRITE":{"hit":[0],"miss":[0],"mshr_merge":[0]},"miss latency":220.01524535493093,"prefetch issued":0,"prefetch requested":0,"useful prefetch":0,"useless prefetch":0},"cores":[{"Avg ROB occupancy at mispredict":180.0,"cycles":365727,"instructions":200004,"mispredict":{"BRANCH_CONDITIONAL":4,"BRANCH_DIRECT_CALL":0,"BRANCH_DIRECT_JUMP":1,"BRANCH_INDIRECT":0,"BRANCH_INDIRECT_CALL":0,"BRANCH_RETURN":0}}],"cpu0_DTLB":{"LOAD":{"hit":[103205],"miss":[1846],"mshr_merge":[354]},"PREFETCH":{"hit":[0],"miss":[0],"mshr_merge":[0]},"RFO":{"hit":[0],"miss":[0],"mshr_merge":[0]},"TRANSLATION":{"hit":[0],"miss":[0],"mshr_merge":[0]},"WRITE":{"hit":[0],"miss":[0],"mshr_merge":[0]},"miss latency":321.9101876675603,"prefetch issued":0,"prefetch requested":0,"useful prefetch":0,"useless prefetch":0},"cpu0_ITLB":{"LOAD":{"hit":[55632],"miss":[0],"mshr_merge":[0]},"PREFETCH":{"hit":[0],"miss":[0],"mshr_merge":[0]},"RFO":{"hit":[0],"miss":[0],"mshr_merge":[0]},"TRANSLATION":{"hit":[0],"miss":[0],"mshr_merge":[0]},"WRITE":{"hit":[0],"miss":[0],"mshr_merge":[0]},"miss latency":null,"prefetch issued":0,"prefetch requested":0,"useful prefetch":0,"useless prefetch":0},"cpu0_L1D":{"LOAD":{"hit":[91873],"miss":[3013],"mshr_merge":[847]},"PREFETCH":{"hit":[212],"miss":[2650],"mshr_merge":[0]},"RFO":{"hit":[0],"miss":[0],"mshr_merge":[0]},"TRANSLATION":{"hit":[536],"miss":[812],"mshr_merge":[0]},"WRITE":{"hit":[12818],"miss":[2],"mshr_merge":[2]},"miss latency":177.88329979879276,"prefetch issued":2862,"prefetch requested":4276,"useful prefetch":1695,"useless prefetch":882},"cpu0_L1I":{"LOAD":{"hit":[62482],"miss":[15],"mshr_merge":[6]},"PREFETCH":{"hit":[0],"miss":[0],"mshr_merge":[0]},"RFO":{"hit":[0],"miss":[0],"mshr_merge":[0]},"TRANSLATION":{"hit":[0],"miss":[0],"mshr_merge":[0]},"WRITE":{"hit":[0],"miss":[0],"mshr_merge":[0]},"miss latency":172.66666666666666,"prefetch issued":0,"prefetch requested":0,"useful prefetch":0,"useless prefetch":0},"cpu0_L2C":{"LOAD":{"hit":[281],"miss":[1894],"mshr_merge":[3]},"PREFETCH":{"hit":[394],"miss":[12133],"mshr_merge":[3139]},"RFO":{"hit":[0],"miss":[0],"mshr_merge":[0]},"TRANSLATION":{"hit":[54],"miss":[758],"mshr_merge":[0]},"WRITE":{"hit":[1646],"miss":[3],"mshr_merge":[0]},"miss latency":189.90885122410546,"prefetch issued":9879,"prefetch requested":10809,"useful prefetch":179,"useless prefetch":2},"cpu0_STLB":{"LOAD":{"hit":[818],"miss":[674],"mshr_merge":[0]},"PREFETCH":{"hit":[0],"miss":[0],"mshr_merge":[0]},"RFO":{"hit":[0],"miss":[0],"mshr_merge":[0]},"TRANSLATION":{"hit":[0],"miss":[0],"mshr_merge":[0]},"WRITE":{"hit":[0],"miss":[0],"mshr_merge":[0]},"miss latency":700.526706231454,"prefetch issued":0,"prefetch requested":0,"useful prefetch":0,"useless prefetch":0}},"traces":["/users/lijrjyan/ChampSim_checkpoint/traces/649.fotonik3d_s-10881B.champsimtrace.xz"]}]