[{"name":"Simulation","roi":{"DRAM":[{"AVG DBUS CONGESTED CYCLE":2.81627486437613,"REFRESHES ISSUED":78,"RQ ROW_BUFFER_HIT":247,"RQ ROW_BUFFER_MISS":7011,"WQ ROW_BUFFER_HIT":0,"WQ ROW_BUFFER_MISS":0}],"LLC":{"LOAD":{"hit":[614],"miss":[3220],"mshr_merge":[364]},"PREFETCH":{"hit":[237],"miss":[2156],"mshr_merge":[270]},"RFO":{"hit":[23],"miss":[839],"mshr_merge":[0]},"TRANSLATION":{"hit":[0],"miss":[1677],"mshr_merge":[0]},"WRITE":{"hit":[10],"miss":[0],"mshr_merge":[0]},"miss latency":187.09954672245468,"prefetch issued":0,"prefetch requested":0,"useful prefetch":0,"useless prefetch":0},"cores":[{"Avg ROB occupancy at mispredict":112.80854700854701,"cycles":945129,"instructions":200000,"mispredict":{"BRANCH_CONDITIONAL":871,"BRANCH_DIRECT_CALL":52,"BRANCH_DIRECT_JUMP":21,"BRANCH_INDIRECT":5,"BRANCH_INDIRECT_CALL":36,"BRANCH_RETURN":185}}],"cpu0_DTLB":{"LOAD":{"hit":[58214],"miss":[5247],"mshr_merge":[1374]},"PREFETCH":{"hit":[0],"miss":[0],"mshr_merge":[0]},"RFO":{"hit":[0],"miss":[0],"mshr_merge":[0]},"TRANSLATION":{"hit":[0],"miss":[0],"mshr_merge":[0]},"WRITE":{"hit":[0],"miss":[0],"mshr_merge":[0]},"miss latency":206.20541237113403,"prefetch issued":0,"prefetch requested":0,"useful prefetch":0,"useless prefetch":0},"cpu0_ITLB":{"LOAD":{"hit":[28241],"miss":[68],"mshr_merge":[23]},"PREFETCH":{"hit":[0],"miss":[0],"mshr_merge":[0]},"RFO":{"hit":[0],"miss":[0],"mshr_merge":[0]},"TRANSLATION":{"hit":[0],"miss":[0],"mshr_merge":[0]},"WRITE":{"hit":[0],"miss":[0],"mshr_merge":[0]},"miss latency":365.68888888888887,"prefetch issued":0,"prefetch requested":0,"useful prefetch":0,"useless prefetch":0},"cpu0_L1D":{"LOAD":{"hit":[30224],"miss":[6007],"mshr_merge":[2003]},"PREFETCH":{"hit":[30],"miss":[69],"mshr_merge":[0]},"RFO":{"hit":[0],"miss":[0],"mshr_merge":[0]},"TRANSLATION":{"hit":[309],"miss":[1717],"mshr_merge":[24]},"WRITE":{"hit":[27291],"miss":[3100],"mshr_merge":[2221]},"miss latency":184.05808119203283,"prefetch issued":99,"prefetch requested":99,"useful prefetch":34,"useless prefetch":7},"cpu0_L1I":{"LOAD":{"hit":[22052],"miss":[134],"mshr_merge":[7]},"PREFETCH":{"hit":[14530],"miss":[0],"mshr_merge":[0]},"RFO":{"hit":[0],"miss":[0],"mshr_merge":[0]},"TRANSLATION":{"hit":[0],"miss":[0],"mshr_merge":[0]},"WRITE":{"hit":[0],"miss":[0],"mshr_merge":[0]},"miss latency":208.04724409448818,"prefetch issued":14530,"prefetch requested":14564,"useful prefetch":0,"useless prefetch":0},"cpu0_L2C":{"LOAD":{"hit":[275],"miss":[3856],"mshr_merge":[22]},"PREFETCH":{"hit":[167],"miss":[2959],"mshr_merge":[566]},"RFO":{"hit":[17],"miss":[862],"mshr_merge":[0]},"TRANSLATION":{"hit":[16],"miss":[1677],"mshr_merge":[0]},"WRITE":{"hit":[1599],"miss":[21],"mshr_merge":[0]},"miss latency":183.39364188873304,"prefetch issued":3057,"prefetch requested":3057,"useful prefetch":121,"useless prefetch":2},"cpu0_STLB":{"LOAD":{"hit":[2931],"miss":[986],"mshr_merge":[0]},"PREFETCH":{"hit":[0],"miss":[0],"mshr_merge":[0]},"RFO":{"hit":[0],"miss":[0],"mshr_merge":[0]},"TRANSLATION":{"hit":[0],"miss":[0],"mshr_merge":[0]},"WRITE":{"hit":[0],"miss":[0],"mshr_merge":[0]},"miss latency":800.7112676056338,"prefetch issued":0,"prefetch requested":0,"useful prefetch":0,"useless prefetch":0}},"sim":{"DRAM":[{"AVG DBUS CONGESTED CYCLE":2.81627486437613,"REFRESHES ISSUED":78,"RQ ROW_BUFFER_HIT":247,"RQ ROW_BUFFER_MISS":7011,"WQ ROW_BUFFER_HIT":0,"WQ ROW_BUFFER_MISS":0}],"LLC":{"LOAD":{"hit":[614],"miss":[3220],"mshr_merge":[364]},"PREFETCH":{"hit":[237],"miss":[2156],"mshr_merge":[270]},"RFO":{"hit":[23],"miss":[839],"mshr_merge":[0]},"TRANSLATION":{"hit":[0],"miss":[1677],"mshr_merge":[0]},"WRITE":{"hit":[10],"miss":[0],"mshr_merge":[0]},"miss latency":187.09954672245468,"prefetch issued":0,"prefetch requested":0,"useful prefetch":0,"useless prefetch":0},"cores":[{"Avg ROB occupancy at mispredict":112.80854700854701,"cycles":945129,"instructions":200000,"mispredict":{"BRANCH_CONDITIONAL":871,"BRANCH_DIRECT_CALL":52,"BRANCH_DIRECT_JUMP":21,"BRANCH_INDIRECT":5,"BRANCH_INDIRECT_CALL":36,"BRANCH_RETURN":185}}],"cpu0_DTLB":{"LOAD":{"hit":[58214],"miss":[5247],"mshr_merge":[1374]},"PREFETCH":{"hit":[0],"miss":[0],"mshr_merge":[0]},"RFO":{"hit":[0],"miss":[0],"mshr_merge":[0]},"TRANSLATION":{"hit":[0],"miss":[0],"mshr_merge":[0]},"WRITE":{"hit":[0],"miss":[0],"mshr_merge":[0]},"miss latency":206.20541237113403,"prefetch issued":0,"prefetch requested":0,"useful prefetch":0,"useless prefetch":0},"cpu0_ITLB":{"LOAD":{"hit":[28241],"miss":[68],"mshr_merge":[23]},"PREFETCH":{"hit":[0],"miss":[0],"mshr_merge":[0]},"RFO":{"hit":[0],"miss":[0],"mshr_merge":[0]},"TRANSLATION":{"hit":[0],"miss":[0],"mshr_merge":[0]},"WRITE":{"hit":[0],"miss":[0],"mshr_merge":[0]},"miss latency":365.68888888888887,"prefetch issued":0,"prefetch requested":0,"useful prefetch":0,"useless prefetch":0},"cpu0_L1D":{"LOAD":{"hit":[30224],"miss":[6007],"mshr_merge":[2003]},"PREFETCH":{"hit":[30],"miss":[69],"mshr_merge":[0]},"RFO":{"hit":[0],"miss":[0],"mshr_merge":[0]},"TRANSLATION":{"hit":[309],"miss":[1717],"mshr_merge":[24]},"WRITE":{"hit":[27291],"miss":[3100],"mshr_merge":[2221]},"miss latency":184.05808119203283,"prefetch issued":99,"prefetch requested":99,"useful prefetch":34,"useless prefetch":7},"cpu0_L1I":{"LOAD":{"hit":[22052],"miss":[134],"mshr_merge":[7]},"PREFETCH":{"hit":[14530],"miss":[0],"mshr_merge":[0]},"RFO":{"hit":[0],"miss":[0],"mshr_merge":[0]},"TRANSLATION":{"hit":[0],"miss":[0],"mshr_merge":[0]},"WRITE":{"hit":[0],"miss":[0],"mshr_merge":[0]},"miss latency":208.04724409448818,"prefetch issued":14530,"prefetch requested":14564,"useful prefetch":0,"useless prefetch":0},"cpu0_L2C":{"LOAD":{"hit":[275],"miss":[3856],"mshr_merge":[22]},"PREFETCH":{"hit":[167],"miss":[2959],"mshr_merge":[566]},"RFO":{"hit":[17],"miss":[862],"mshr_merge":[0]},"TRANSLATION":{"hit":[16],"miss":[1677],"mshr_merge":[0]},"WRITE":{"hit":[1599],"miss":[21],"mshr_merge":[0]},"miss latency":183.39364188873304,"prefetch issued":3057,"prefetch requested":3057,"useful prefetch":121,"useless prefetch":2},"cpu0_STLB":{"LOAD":{"hit":[2931],"miss":[986],"mshr_merge":[0]},"PREFETCH":{"hit":[0],"miss":[0],"mshr_merge":[0]},"RFO":{"hit":[0],"miss":[0],"mshr_merge":[0]},"TRANSLATION":{"hit":[0],"miss":[0],"mshr_merge":[0]},"WRITE":{"hit":[0],"miss":[0],"mshr_merge":[0]},"miss latency":800.7112676056338,"prefetch issued":0,"prefetch requested":0,"useful prefetch":0,"useless prefetch":0}},"traces":["/users/lijrjyan/ChampSim_checkpoint/traces/471.omnetpp-188B.champsimtrace.xz"]}]