[{"name":"Simulation","roi":{"DRAM":[{"AVG DBUS CONGESTED CYCLE":2.9694055944055946,"REFRESHES ISSUED":17,"RQ ROW_BUFFER_HIT":47,"RQ ROW_BUFFER_MISS":1611,"WQ ROW_BUFFER_HIT":0,"WQ ROW_BUFFER_MISS":0}],"LLC":{"LOAD":{"hit":[249],"miss":[510],"mshr_merge":[47]},"PREFETCH":{"hit":[560],"miss":[916],"mshr_merge":[233]},"RFO":{"hit":[0],"miss":[347],"mshr_merge":[0]},"TRANSLATION":{"hit":[0],"miss":[165],"mshr_merge":[0]},"WRITE":{"hit":[0],"miss":[0],"mshr_merge":[0]},"miss latency":205.755859375,"prefetch issued":0,"prefetch requested":0,"useful prefetch":0,"useless prefetch":0},"cores":[{"Avg ROB occupancy at mispredict":79.26119402985074,"cycles":206047,"instructions":200001,"mispredict":{"BRANCH_CONDITIONAL":449,"BRANCH_DIRECT_CALL":171,"BRANCH_DIRECT_JUMP":24,"BRANCH_INDIRECT":0,"BRANCH_INDIRECT_CALL":0,"BRANCH_RETURN":160}}],"cpu0_DTLB":{"LOAD":{"hit":[62558],"miss":[504],"mshr_merge":[203]},"PREFETCH":{"hit":[0],"miss":[0],"mshr_merge":[0]},"RFO":{"hit":[0],"miss":[0],"mshr_merge":[0]},"TRANSLATION":{"hit":[0],"miss":[0],"mshr_merge":[0]},"WRITE":{"hit":[0],"miss":[0],"mshr_merge":[0]},"miss latency":280.8673139158576,"prefetch issued":0,"prefetch requested":0,"useful prefetch":0,"useless prefetch":0},"cpu0_ITLB":{"LOAD":{"hit":[24281],"miss":[53],"mshr_merge":[33]},"PREFETCH":{"hit":[0],"miss":[0],"mshr_merge":[0]},"RFO":{"hit":[0],"miss":[0],"mshr_merge":[0]},"TRANSLATION":{"hit":[0],"miss":[0],"mshr_merge":[0]},"WRITE":{"hit":[0],"miss":[0],"mshr_merge":[0]},"miss latency":718.35,"prefetch issued":0,"prefetch requested":0,"useful prefetch":0,"useless prefetch":0},"cpu0_L1D":{"LOAD":{"hit":[38448],"miss":[729],"mshr_merge":[92]},"PREFETCH":{"hit":[410],"miss":[243],"mshr_merge":[4]},"RFO":{"hit":[0],"miss":[0],"mshr_merge":[0]},"TRANSLATION":{"hit":[68],"miss":[183],"mshr_merge":[13]},"WRITE":{"hit":[30356],"miss":[837],"mshr_merge":[403]},"miss latency":159.82263242375603,"prefetch issued":653,"prefetch requested":772,"useful prefetch":94,"useless prefetch":108},"cpu0_L1I":{"LOAD":{"hit":[27995],"miss":[560],"mshr_merge":[130]},"PREFETCH":{"hit":[137],"miss":[138],"mshr_merge":[2]},"RFO":{"hit":[0],"miss":[0],"mshr_merge":[0]},"TRANSLATION":{"hit":[0],"miss":[0],"mshr_merge":[0]},"WRITE":{"hit":[0],"miss":[0],"mshr_merge":[0]},"miss latency":108.39260969976905,"prefetch issued":275,"prefetch requested":275,"useful prefetch":123,"useless prefetch":13},"cpu0_L2C":{"LOAD":{"hit":[301],"miss":[766],"mshr_merge":[7]},"PREFETCH":{"hit":[361],"miss":[1668],"mshr_merge":[192]},"RFO":{"hit":[87],"miss":[347],"mshr_merge":[0]},"TRANSLATION":{"hit":[5],"miss":[165],"mshr_merge":[0]},"WRITE":{"hit":[133],"miss":[0],"mshr_merge":[0]},"miss latency":180.81171875,"prefetch issued":1654,"prefetch requested":1792,"useful prefetch":54,"useless prefetch":0},"cpu0_STLB":{"LOAD":{"hit":[214],"miss":[107],"mshr_merge":[0]},"PREFETCH":{"hit":[0],"miss":[0],"mshr_merge":[0]},"RFO":{"hit":[0],"miss":[0],"mshr_merge":[0]},"TRANSLATION":{"hit":[0],"miss":[0],"mshr_merge":[0]},"WRITE":{"hit":[0],"miss":[0],"mshr_merge":[0]},"miss latency":864.5739130434782,"prefetch issued":0,"prefetch requested":0,"useful prefetch":0,"useless prefetch":0}},"sim":{"DRAM":[{"AVG DBUS CONGESTED CYCLE":2.9694055944055946,"REFRESHES ISSUED":17,"RQ ROW_BUFFER_HIT":47,"RQ ROW_BUFFER_MISS":1611,"WQ ROW_BUFFER_HIT":0,"WQ ROW_BUFFER_MISS":0}],"LLC":{"LOAD":{"hit":[249],"miss":[510],"mshr_merge":[47]},"PREFETCH":{"hit":[560],"miss":[916],"mshr_merge":[233]},"RFO":{"hit":[0],"miss":[347],"mshr_merge":[0]},"TRANSLATION":{"hit":[0],"miss":[165],"mshr_merge":[0]},"WRITE":{"hit":[0],"miss":[0],"mshr_merge":[0]},"miss latency":205.755859375,"prefetch issued":0,"prefetch requested":0,"useful prefetch":0,"useless prefetch":0},"cores":[{"Avg ROB occupancy at mispredict":79.26119402985074,"cycles":206047,"instructions":200001,"mispredict":{"BRANCH_CONDITIONAL":449,"BRANCH_DIRECT_CALL":171,"BRANCH_DIRECT_JUMP":24,"BRANCH_INDIRECT":0,"BRANCH_INDIRECT_CALL":0,"BRANCH_RETURN":160}}],"cpu0_DTLB":{"LOAD":{"hit":[62558],"miss":[504],"mshr_merge":[203]},"PREFETCH":{"hit":[0],"miss":[0],"mshr_merge":[0]},"RFO":{"hit":[0],"miss":[0],"mshr_merge":[0]},"TRANSLATION":{"hit":[0],"miss":[0],"mshr_merge":[0]},"WRITE":{"hit":[0],"miss":[0],"mshr_merge":[0]},"miss latency":280.8673139158576,"prefetch issued":0,"prefetch requested":0,"useful prefetch":0,"useless prefetch":0},"cpu0_ITLB":{"LOAD":{"hit":[24281],"miss":[53],"mshr_merge":[33]},"PREFETCH":{"hit":[0],"miss":[0],"mshr_merge":[0]},"RFO":{"hit":[0],"miss":[0],"mshr_merge":[0]},"TRANSLATION":{"hit":[0],"miss":[0],"mshr_merge":[0]},"WRITE":{"hit":[0],"miss":[0],"mshr_merge":[0]},"miss latency":718.35,"prefetch issued":0,"prefetch requested":0,"useful prefetch":0,"useless prefetch":0},"cpu0_L1D":{"LOAD":{"hit":[38448],"miss":[729],"mshr_merge":[92]},"PREFETCH":{"hit":[410],"miss":[243],"mshr_merge":[4]},"RFO":{"hit":[0],"miss":[0],"mshr_merge":[0]},"TRANSLATION":{"hit":[68],"miss":[183],"mshr_merge":[13]},"WRITE":{"hit":[30356],"miss":[837],"mshr_merge":[403]},"miss latency":159.82263242375603,"prefetch issued":653,"prefetch requested":772,"useful prefetch":94,"useless prefetch":108},"cpu0_L1I":{"LOAD":{"hit":[27995],"miss":[560],"mshr_merge":[130]},"PREFETCH":{"hit":[137],"miss":[138],"mshr_merge":[2]},"RFO":{"hit":[0],"miss":[0],"mshr_merge":[0]},"TRANSLATION":{"hit":[0],"miss":[0],"mshr_merge":[0]},"WRITE":{"hit":[0],"miss":[0],"mshr_merge":[0]},"miss latency":108.39260969976905,"prefetch issued":275,"prefetch requested":275,"useful prefetch":123,"useless prefetch":13},"cpu0_L2C":{"LOAD":{"hit":[301],"miss":[766],"mshr_merge":[7]},"PREFETCH":{"hit":[361],"miss":[1668],"mshr_merge":[192]},"RFO":{"hit":[87],"miss":[347],"mshr_merge":[0]},"TRANSLATION":{"hit":[5],"miss":[165],"mshr_merge":[0]},"WRITE":{"hit":[133],"miss":[0],"mshr_merge":[0]},"miss latency":180.81171875,"prefetch issued":1654,"prefetch requested":1792,"useful prefetch":54,"useless prefetch":0},"cpu0_STLB":{"LOAD":{"hit":[214],"miss":[107],"mshr_merge":[0]},"PREFETCH":{"hit":[0],"miss":[0],"mshr_merge":[0]},"RFO":{"hit":[0],"miss":[0],"mshr_merge":[0]},"TRANSLATION":{"hit":[0],"miss":[0],"mshr_merge":[0]},"WRITE":{"hit":[0],"miss":[0],"mshr_merge":[0]},"miss latency":864.5739130434782,"prefetch issued":0,"prefetch requested":0,"useful prefetch":0,"useless prefetch":0}},"traces":["/users/lijrjyan/ChampSim_checkpoint/traces/481.wrf-1170B.champsimtrace.xz"]}]