[{"name":"Simulation","roi":{"DRAM":[{"AVG DBUS CONGESTED CYCLE":2.8728323699421967,"REFRESHES ISSUED":14,"RQ ROW_BUFFER_HIT":14,"RQ ROW_BUFFER_MISS":205,"WQ ROW_BUFFER_HIT":0,"WQ ROW_BUFFER_MISS":0}],"LLC":{"LOAD":{"hit":[27],"miss":[97],"mshr_merge":[19]},"PREFETCH":{"hit":[46],"miss":[151],"mshr_merge":[66]},"RFO":{"hit":[0],"miss":[14],"mshr_merge":[0]},"TRANSLATION":{"hit":[0],"miss":[42],"mshr_merge":[0]},"WRITE":{"hit":[0],"miss":[0],"mshr_merge":[0]},"miss latency":168.46451612903226,"prefetch issued":0,"prefetch requested":0,"useful prefetch":0,"useless prefetch":0},"cores":[{"Avg ROB occupancy at mispredict":96.0993278566094,"cycles":167709,"instructions":200002,"mispredict":{"BRANCH_CONDITIONAL":1173,"BRANCH_DIRECT_CALL":78,"BRANCH_DIRECT_JUMP":9,"BRANCH_INDIRECT":0,"BRANCH_INDIRECT_CALL":0,"BRANCH_RETURN":79}}],"cpu0_DTLB":{"LOAD":{"hit":[36508],"miss":[19],"mshr_merge":[2]},"PREFETCH":{"hit":[0],"miss":[0],"mshr_merge":[0]},"RFO":{"hit":[0],"miss":[0],"mshr_merge":[0]},"TRANSLATION":{"hit":[0],"miss":[0],"mshr_merge":[0]},"WRITE":{"hit":[0],"miss":[0],"mshr_merge":[0]},"miss latency":925.6111111111111,"prefetch issued":0,"prefetch requested":0,"useful prefetch":0,"useless prefetch":0},"cpu0_ITLB":{"LOAD":{"hit":[6809],"miss":[10],"mshr_merge":[7]},"PREFETCH":{"hit":[0],"miss":[0],"mshr_merge":[0]},"RFO":{"hit":[0],"miss":[0],"mshr_merge":[0]},"TRANSLATION":{"hit":[0],"miss":[0],"mshr_merge":[0]},"WRITE":{"hit":[0],"miss":[0],"mshr_merge":[0]},"miss latency":714.3333333333334,"prefetch issued":0,"prefetch requested":0,"useful prefetch":0,"useless prefetch":0},"cpu0_L1D":{"LOAD":{"hit":[29398],"miss":[38],"mshr_merge":[9]},"PREFETCH":{"hit":[0],"miss":[8],"mshr_merge":[0]},"RFO":{"hit":[0],"miss":[0],"mshr_merge":[0]},"TRANSLATION":{"hit":[2],"miss":[43],"mshr_merge":[1]},"WRITE":{"hit":[7636],"miss":[20],"mshr_merge":[6]},"miss latency":213.88235294117646,"prefetch issued":8,"prefetch requested":8,"useful prefetch":0,"useless prefetch":0},"cpu0_L1I":{"LOAD":{"hit":[4716],"miss":[148],"mshr_merge":[30]},"PREFETCH":{"hit":[4008],"miss":[0],"mshr_merge":[0]},"RFO":{"hit":[0],"miss":[0],"mshr_merge":[0]},"TRANSLATION":{"hit":[0],"miss":[0],"mshr_merge":[0]},"WRITE":{"hit":[0],"miss":[0],"mshr_merge":[0]},"miss latency":106.90082644628099,"prefetch issued":4008,"prefetch requested":4249,"useful prefetch":0,"useless prefetch":0},"cpu0_L2C":{"LOAD":{"hit":[22],"miss":[126],"mshr_merge":[2]},"PREFETCH":{"hit":[2],"miss":[241],"mshr_merge":[44]},"RFO":{"hit":[0],"miss":[14],"mshr_merge":[0]},"TRANSLATION":{"hit":[0],"miss":[42],"mshr_merge":[0]},"WRITE":{"hit":[0],"miss":[0],"mshr_merge":[0]},"miss latency":159.80978260869566,"prefetch issued":233,"prefetch requested":233,"useful prefetch":24,"useless prefetch":0},"cpu0_STLB":{"LOAD":{"hit":[0],"miss":[20],"mshr_merge":[0]},"PREFETCH":{"hit":[0],"miss":[0],"mshr_merge":[0]},"RFO":{"hit":[0],"miss":[0],"mshr_merge":[0]},"TRANSLATION":{"hit":[0],"miss":[0],"mshr_merge":[0]},"WRITE":{"hit":[0],"miss":[0],"mshr_merge":[0]},"miss latency":889.6190476190476,"prefetch issued":0,"prefetch requested":0,"useful prefetch":0,"useless prefetch":0}},"sim":{"DRAM":[{"AVG DBUS CONGESTED CYCLE":2.8728323699421967,"REFRESHES ISSUED":14,"RQ ROW_BUFFER_HIT":14,"RQ ROW_BUFFER_MISS":205,"WQ ROW_BUFFER_HIT":0,"WQ ROW_BUFFER_MISS":0}],"LLC":{"LOAD":{"hit":[27],"miss":[97],"mshr_merge":[19]},"PREFETCH":{"hit":[46],"miss":[151],"mshr_merge":[66]},"RFO":{"hit":[0],"miss":[14],"mshr_merge":[0]},"TRANSLATION":{"hit":[0],"miss":[42],"mshr_merge":[0]},"WRITE":{"hit":[0],"miss":[0],"mshr_merge":[0]},"miss latency":168.46451612903226,"prefetch issued":0,"prefetch requested":0,"useful prefetch":0,"useless prefetch":0},"cores":[{"Avg ROB occupancy at mispredict":96.0993278566094,"cycles":167709,"instructions":200002,"mispredict":{"BRANCH_CONDITIONAL":1173,"BRANCH_DIRECT_CALL":78,"BRANCH_DIRECT_JUMP":9,"BRANCH_INDIRECT":0,"BRANCH_INDIRECT_CALL":0,"BRANCH_RETURN":79}}],"cpu0_DTLB":{"LOAD":{"hit":[36508],"miss":[19],"mshr_merge":[2]},"PREFETCH":{"hit":[0],"miss":[0],"mshr_merge":[0]},"RFO":{"hit":[0],"miss":[0],"mshr_merge":[0]},"TRANSLATION":{"hit":[0],"miss":[0],"mshr_merge":[0]},"WRITE":{"hit":[0],"miss":[0],"mshr_merge":[0]},"miss latency":925.6111111111111,"prefetch issued":0,"prefetch requested":0,"useful prefetch":0,"useless prefetch":0},"cpu0_ITLB":{"LOAD":{"hit":[6809],"miss":[10],"mshr_merge":[7]},"PREFETCH":{"hit":[0],"miss":[0],"mshr_merge":[0]},"RFO":{"hit":[0],"miss":[0],"mshr_merge":[0]},"TRANSLATION":{"hit":[0],"miss":[0],"mshr_merge":[0]},"WRITE":{"hit":[0],"miss":[0],"mshr_merge":[0]},"miss latency":714.3333333333334,"prefetch issued":0,"prefetch requested":0,"useful prefetch":0,"useless prefetch":0},"cpu0_L1D":{"LOAD":{"hit":[29398],"miss":[38],"mshr_merge":[9]},"PREFETCH":{"hit":[0],"miss":[8],"mshr_merge":[0]},"RFO":{"hit":[0],"miss":[0],"mshr_merge":[0]},"TRANSLATION":{"hit":[2],"miss":[43],"mshr_merge":[1]},"WRITE":{"hit":[7636],"miss":[20],"mshr_merge":[6]},"miss latency":213.88235294117646,"prefetch issued":8,"prefetch requested":8,"useful prefetch":0,"useless prefetch":0},"cpu0_L1I":{"LOAD":{"hit":[4716],"miss":[148],"mshr_merge":[30]},"PREFETCH":{"hit":[4008],"miss":[0],"mshr_merge":[0]},"RFO":{"hit":[0],"miss":[0],"mshr_merge":[0]},"TRANSLATION":{"hit":[0],"miss":[0],"mshr_merge":[0]},"WRITE":{"hit":[0],"miss":[0],"mshr_merge":[0]},"miss latency":106.90082644628099,"prefetch issued":4008,"prefetch requested":4249,"useful prefetch":0,"useless prefetch":0},"cpu0_L2C":{"LOAD":{"hit":[22],"miss":[126],"mshr_merge":[2]},"PREFETCH":{"hit":[2],"miss":[241],"mshr_merge":[44]},"RFO":{"hit":[0],"miss":[14],"mshr_merge":[0]},"TRANSLATION":{"hit":[0],"miss":[42],"mshr_merge":[0]},"WRITE":{"hit":[0],"miss":[0],"mshr_merge":[0]},"miss latency":159.80978260869566,"prefetch issued":233,"prefetch requested":233,"useful prefetch":24,"useless prefetch":0},"cpu0_STLB":{"LOAD":{"hit":[0],"miss":[20],"mshr_merge":[0]},"PREFETCH":{"hit":[0],"miss":[0],"mshr_merge":[0]},"RFO":{"hit":[0],"miss":[0],"mshr_merge":[0]},"TRANSLATION":{"hit":[0],"miss":[0],"mshr_merge":[0]},"WRITE":{"hit":[0],"miss":[0],"mshr_merge":[0]},"miss latency":889.6190476190476,"prefetch issued":0,"prefetch requested":0,"useful prefetch":0,"useless prefetch":0}},"traces":["/users/lijrjyan/ChampSim_checkpoint/traces/621.wrf_s-575B.champsimtrace.xz"]}]