[{"name":"Simulation","roi":{"DRAM":[{"AVG DBUS CONGESTED CYCLE":2.931794333683106,"REFRESHES ISSUED":16,"RQ ROW_BUFFER_HIT":93,"RQ ROW_BUFFER_MISS":3920,"WQ ROW_BUFFER_HIT":0,"WQ ROW_BUFFER_MISS":0}],"LLC":{"LOAD":{"hit":[1115],"miss":[1060],"mshr_merge":[229]},"PREFETCH":{"hit":[4956],"miss":[4177],"mshr_merge":[1542]},"RFO":{"hit":[1],"miss":[155],"mshr_merge":[0]},"TRANSLATION":{"hit":[0],"miss":[392],"mshr_merge":[0]},"WRITE":{"hit":[1],"miss":[0],"mshr_merge":[0]},"miss latency":216.889234598631,"prefetch issued":0,"prefetch requested":0,"useful prefetch":0,"useless prefetch":0},"cores":[{"Avg ROB occupancy at mispredict":289.8588235294118,"cycles":192389,"instructions":200004,"mispredict":{"BRANCH_CONDITIONAL":83,"BRANCH_DIRECT_CALL":5,"BRANCH_DIRECT_JUMP":4,"BRANCH_INDIRECT":1,"BRANCH_INDIRECT_CALL":0,"BRANCH_RETURN":77}}],"cpu0_DTLB":{"LOAD":{"hit":[63259],"miss":[8522],"mshr_merge":[963]},"PREFETCH":{"hit":[0],"miss":[0],"mshr_merge":[0]},"RFO":{"hit":[0],"miss":[0],"mshr_merge":[0]},"TRANSLATION":{"hit":[0],"miss":[0],"mshr_merge":[0]},"WRITE":{"hit":[0],"miss":[0],"mshr_merge":[0]},"miss latency":30.24811632518176,"prefetch issued":0,"prefetch requested":0,"useful prefetch":0,"useless prefetch":0},"cpu0_ITLB":{"LOAD":{"hit":[40016],"miss":[69],"mshr_merge":[55]},"PREFETCH":{"hit":[0],"miss":[0],"mshr_merge":[0]},"RFO":{"hit":[0],"miss":[0],"mshr_merge":[0]},"TRANSLATION":{"hit":[0],"miss":[0],"mshr_merge":[0]},"WRITE":{"hit":[0],"miss":[0],"mshr_merge":[0]},"miss latency":876.8571428571429,"prefetch issued":0,"prefetch requested":0,"useful prefetch":0,"useless prefetch":0},"cpu0_L1D":{"LOAD":{"hit":[47082],"miss":[12772],"mshr_merge":[831]},"PREFETCH":{"hit":[0],"miss":[0],"mshr_merge":[0]},"RFO":{"hit":[0],"miss":[0],"mshr_merge":[0]},"TRANSLATION":{"hit":[48],"miss":[408],"mshr_merge":[16]},"WRITE":{"hit":[14871],"miss":[1193],"mshr_merge":[121]},"miss latency":34.788079964195134,"prefetch issued":0,"prefetch requested":0,"useful prefetch":0,"useless prefetch":0},"cpu0_L1I":{"LOAD":{"hit":[43549],"miss":[1250],"mshr_merge":[661]},"PREFETCH":{"hit":[2464],"miss":[4469],"mshr_merge":[239]},"RFO":{"hit":[0],"miss":[0],"mshr_merge":[0]},"TRANSLATION":{"hit":[0],"miss":[0],"mshr_merge":[0]},"WRITE":{"hit":[0],"miss":[0],"mshr_merge":[0]},"miss latency":79.3041018387553,"prefetch issued":6933,"prefetch requested":6933,"useful prefetch":4060,"useless prefetch":168},"cpu0_L2C":{"LOAD":{"hit":[10285],"miss":[2245],"mshr_merge":[70]},"PREFETCH":{"hit":[11873],"miss":[10211],"mshr_merge":[1078]},"RFO":{"hit":[916],"miss":[156],"mshr_merge":[0]},"TRANSLATION":{"hit":[1],"miss":[392],"mshr_merge":[0]},"WRITE":{"hit":[1085],"miss":[3],"mshr_merge":[0]},"miss latency":142.12267525035764,"prefetch issued":17854,"prefetch requested":20211,"useful prefetch":142,"useless prefetch":0},"cpu0_STLB":{"LOAD":{"hit":[7380],"miss":[193],"mshr_merge":[0]},"PREFETCH":{"hit":[0],"miss":[0],"mshr_merge":[0]},"RFO":{"hit":[0],"miss":[0],"mshr_merge":[0]},"TRANSLATION":{"hit":[0],"miss":[0],"mshr_merge":[0]},"WRITE":{"hit":[0],"miss":[0],"mshr_merge":[0]},"miss latency":1018.6130653266332,"prefetch issued":0,"prefetch requested":0,"useful prefetch":0,"useless prefetch":0}},"sim":{"DRAM":[{"AVG DBUS CONGESTED CYCLE":2.931794333683106,"REFRESHES ISSUED":16,"RQ ROW_BUFFER_HIT":93,"RQ ROW_BUFFER_MISS":3920,"WQ ROW_BUFFER_HIT":0,"WQ ROW_BUFFER_MISS":0}],"LLC":{"LOAD":{"hit":[1115],"miss":[1060],"mshr_merge":[229]},"PREFETCH":{"hit":[4956],"miss":[4177],"mshr_merge":[1542]},"RFO":{"hit":[1],"miss":[155],"mshr_merge":[0]},"TRANSLATION":{"hit":[0],"miss":[392],"mshr_merge":[0]},"WRITE":{"hit":[1],"miss":[0],"mshr_merge":[0]},"miss latency":216.889234598631,"prefetch issued":0,"prefetch requested":0,"useful prefetch":0,"useless prefetch":0},"cores":[{"Avg ROB occupancy at mispredict":289.8588235294118,"cycles":192389,"instructions":200004,"mispredict":{"BRANCH_CONDITIONAL":83,"BRANCH_DIRECT_CALL":5,"BRANCH_DIRECT_JUMP":4,"BRANCH_INDIRECT":1,"BRANCH_INDIRECT_CALL":0,"BRANCH_RETURN":77}}],"cpu0_DTLB":{"LOAD":{"hit":[63259],"miss":[8522],"mshr_merge":[963]},"PREFETCH":{"hit":[0],"miss":[0],"mshr_merge":[0]},"RFO":{"hit":[0],"miss":[0],"mshr_merge":[0]},"TRANSLATION":{"hit":[0],"miss":[0],"mshr_merge":[0]},"WRITE":{"hit":[0],"miss":[0],"mshr_merge":[0]},"miss latency":30.24811632518176,"prefetch issued":0,"prefetch requested":0,"useful prefetch":0,"useless prefetch":0},"cpu0_ITLB":{"LOAD":{"hit":[40016],"miss":[69],"mshr_merge":[55]},"PREFETCH":{"hit":[0],"miss":[0],"mshr_merge":[0]},"RFO":{"hit":[0],"miss":[0],"mshr_merge":[0]},"TRANSLATION":{"hit":[0],"miss":[0],"mshr_merge":[0]},"WRITE":{"hit":[0],"miss":[0],"mshr_merge":[0]},"miss latency":876.8571428571429,"prefetch issued":0,"prefetch requested":0,"useful prefetch":0,"useless prefetch":0},"cpu0_L1D":{"LOAD":{"hit":[47082],"miss":[12772],"mshr_merge":[831]},"PREFETCH":{"hit":[0],"miss":[0],"mshr_merge":[0]},"RFO":{"hit":[0],"miss":[0],"mshr_merge":[0]},"TRANSLATION":{"hit":[48],"miss":[408],"mshr_merge":[16]},"WRITE":{"hit":[14871],"miss":[1193],"mshr_merge":[121]},"miss latency":34.788079964195134,"prefetch issued":0,"prefetch requested":0,"useful prefetch":0,"useless prefetch":0},"cpu0_L1I":{"LOAD":{"hit":[43549],"miss":[1250],"mshr_merge":[661]},"PREFETCH":{"hit":[2464],"miss":[4469],"mshr_merge":[239]},"RFO":{"hit":[0],"miss":[0],"mshr_merge":[0]},"TRANSLATION":{"hit":[0],"miss":[0],"mshr_merge":[0]},"WRITE":{"hit":[0],"miss":[0],"mshr_merge":[0]},"miss latency":79.3041018387553,"prefetch issued":6933,"prefetch requested":6933,"useful prefetch":4060,"useless prefetch":168},"cpu0_L2C":{"LOAD":{"hit":[10285],"miss":[2245],"mshr_merge":[70]},"PREFETCH":{"hit":[11873],"miss":[10211],"mshr_merge":[1078]},"RFO":{"hit":[916],"miss":[156],"mshr_merge":[0]},"TRANSLATION":{"hit":[1],"miss":[392],"mshr_merge":[0]},"WRITE":{"hit":[1085],"miss":[3],"mshr_merge":[0]},"miss latency":142.12267525035764,"prefetch issued":17854,"prefetch requested":20211,"useful prefetch":142,"useless prefetch":0},"cpu0_STLB":{"LOAD":{"hit":[7380],"miss":[193],"mshr_merge":[0]},"PREFETCH":{"hit":[0],"miss":[0],"mshr_merge":[0]},"RFO":{"hit":[0],"miss":[0],"mshr_merge":[0]},"TRANSLATION":{"hit":[0],"miss":[0],"mshr_merge":[0]},"WRITE":{"hit":[0],"miss":[0],"mshr_merge":[0]},"miss latency":1018.6130653266332,"prefetch issued":0,"prefetch requested":0,"useful prefetch":0,"useless prefetch":0}},"traces":["/users/lijrjyan/ChampSim_checkpoint/traces/607.cactuBSSN_s-2421B.champsimtrace.xz"]}]