[{"name":"Simulation","roi":{"DRAM":[{"AVG DBUS CONGESTED CYCLE":2.942711398862076,"REFRESHES ISSUED":16,"RQ ROW_BUFFER_HIT":74,"RQ ROW_BUFFER_MISS":3650,"WQ ROW_BUFFER_HIT":0,"WQ ROW_BUFFER_MISS":0}],"LLC":{"LOAD":{"hit":[754],"miss":[1208],"mshr_merge":[131]},"PREFETCH":{"hit":[2033],"miss":[3346],"mshr_merge":[1231]},"RFO":{"hit":[0],"miss":[137],"mshr_merge":[0]},"TRANSLATION":{"hit":[0],"miss":[404],"mshr_merge":[0]},"WRITE":{"hit":[0],"miss":[0],"mshr_merge":[0]},"miss latency":226.05371428571428,"prefetch issued":0,"prefetch requested":0,"useful prefetch":0,"useless prefetch":0},"cores":[{"Avg ROB occupancy at mispredict":288.36309523809524,"cycles":192233,"instructions":200001,"mispredict":{"BRANCH_CONDITIONAL":81,"BRANCH_DIRECT_CALL":5,"BRANCH_DIRECT_JUMP":5,"BRANCH_INDIRECT":2,"BRANCH_INDIRECT_CALL":0,"BRANCH_RETURN":75}}],"cpu0_DTLB":{"LOAD":{"hit":[63206],"miss":[8520],"mshr_merge":[1117]},"PREFETCH":{"hit":[0],"miss":[0],"mshr_merge":[0]},"RFO":{"hit":[0],"miss":[0],"mshr_merge":[0]},"TRANSLATION":{"hit":[0],"miss":[0],"mshr_merge":[0]},"WRITE":{"hit":[0],"miss":[0],"mshr_merge":[0]},"miss latency":33.773021874156086,"prefetch issued":0,"prefetch requested":0,"useful prefetch":0,"useless prefetch":0},"cpu0_ITLB":{"LOAD":{"hit":[39586],"miss":[66],"mshr_merge":[52]},"PREFETCH":{"hit":[0],"miss":[0],"mshr_merge":[0]},"RFO":{"hit":[0],"miss":[0],"mshr_merge":[0]},"TRANSLATION":{"hit":[0],"miss":[0],"mshr_merge":[0]},"WRITE":{"hit":[0],"miss":[0],"mshr_merge":[0]},"miss latency":797.7142857142857,"prefetch issued":0,"prefetch requested":0,"useful prefetch":0,"useless prefetch":0},"cpu0_L1D":{"LOAD":{"hit":[47983],"miss":[11875],"mshr_merge":[1106]},"PREFETCH":{"hit":[1275],"miss":[1880],"mshr_merge":[304]},"RFO":{"hit":[0],"miss":[0],"mshr_merge":[0]},"TRANSLATION":{"hit":[57],"miss":[439],"mshr_merge":[32]},"WRITE":{"hit":[14941],"miss":[1085],"mshr_merge":[58]},"miss latency":40.76868525896414,"prefetch issued":3155,"prefetch requested":3441,"useful prefetch":795,"useless prefetch":759},"cpu0_L1I":{"LOAD":{"hit":[43630],"miss":[1033],"mshr_merge":[517]},"PREFETCH":{"hit":[1877],"miss":[4773],"mshr_merge":[142]},"RFO":{"hit":[0],"miss":[0],"mshr_merge":[0]},"TRANSLATION":{"hit":[0],"miss":[0],"mshr_merge":[0]},"WRITE":{"hit":[0],"miss":[0],"mshr_merge":[0]},"miss latency":107.32486388384756,"prefetch issued":6650,"prefetch requested":6650,"useful prefetch":4589,"useless prefetch":41},"cpu0_L2C":{"LOAD":{"hit":[9242],"miss":[2042],"mshr_merge":[80]},"PREFETCH":{"hit":[13765],"miss":[6699],"mshr_merge":[1319]},"RFO":{"hit":[890],"miss":[137],"mshr_merge":[0]},"TRANSLATION":{"hit":[3],"miss":[404],"mshr_merge":[0]},"WRITE":{"hit":[1065],"miss":[0],"mshr_merge":[0]},"miss latency":171.78104448742747,"prefetch issued":14247,"prefetch requested":14996,"useful prefetch":138,"useless prefetch":0},"cpu0_STLB":{"LOAD":{"hit":[7209],"miss":[208],"mshr_merge":[0]},"PREFETCH":{"hit":[0],"miss":[0],"mshr_merge":[0]},"RFO":{"hit":[0],"miss":[0],"mshr_merge":[0]},"TRANSLATION":{"hit":[0],"miss":[0],"mshr_merge":[0]},"WRITE":{"hit":[0],"miss":[0],"mshr_merge":[0]},"miss latency":1060.052132701422,"prefetch issued":0,"prefetch requested":0,"useful prefetch":0,"useless prefetch":0}},"sim":{"DRAM":[{"AVG DBUS CONGESTED CYCLE":2.942711398862076,"REFRESHES ISSUED":16,"RQ ROW_BUFFER_HIT":74,"RQ ROW_BUFFER_MISS":3650,"WQ ROW_BUFFER_HIT":0,"WQ ROW_BUFFER_MISS":0}],"LLC":{"LOAD":{"hit":[754],"miss":[1208],"mshr_merge":[131]},"PREFETCH":{"hit":[2033],"miss":[3346],"mshr_merge":[1231]},"RFO":{"hit":[0],"miss":[137],"mshr_merge":[0]},"TRANSLATION":{"hit":[0],"miss":[404],"mshr_merge":[0]},"WRITE":{"hit":[0],"miss":[0],"mshr_merge":[0]},"miss latency":226.05371428571428,"prefetch issued":0,"prefetch requested":0,"useful prefetch":0,"useless prefetch":0},"cores":[{"Avg ROB occupancy at mispredict":288.36309523809524,"cycles":192233,"instructions":200001,"mispredict":{"BRANCH_CONDITIONAL":81,"BRANCH_DIRECT_CALL":5,"BRANCH_DIRECT_JUMP":5,"BRANCH_INDIRECT":2,"BRANCH_INDIRECT_CALL":0,"BRANCH_RETURN":75}}],"cpu0_DTLB":{"LOAD":{"hit":[63206],"miss":[8520],"mshr_merge":[1117]},"PREFETCH":{"hit":[0],"miss":[0],"mshr_merge":[0]},"RFO":{"hit":[0],"miss":[0],"mshr_merge":[0]},"TRANSLATION":{"hit":[0],"miss":[0],"mshr_merge":[0]},"WRITE":{"hit":[0],"miss":[0],"mshr_merge":[0]},"miss latency":33.773021874156086,"prefetch issued":0,"prefetch requested":0,"useful prefetch":0,"useless prefetch":0},"cpu0_ITLB":{"LOAD":{"hit":[39586],"miss":[66],"mshr_merge":[52]},"PREFETCH":{"hit":[0],"miss":[0],"mshr_merge":[0]},"RFO":{"hit":[0],"miss":[0],"mshr_merge":[0]},"TRANSLATION":{"hit":[0],"miss":[0],"mshr_merge":[0]},"WRITE":{"hit":[0],"miss":[0],"mshr_merge":[0]},"miss latency":797.7142857142857,"prefetch issued":0,"prefetch requested":0,"useful prefetch":0,"useless prefetch":0},"cpu0_L1D":{"LOAD":{"hit":[47983],"miss":[11875],"mshr_merge":[1106]},"PREFETCH":{"hit":[1275],"miss":[1880],"mshr_merge":[304]},"RFO":{"hit":[0],"miss":[0],"mshr_merge":[0]},"TRANSLATION":{"hit":[57],"miss":[439],"mshr_merge":[32]},"WRITE":{"hit":[14941],"miss":[1085],"mshr_merge":[58]},"miss latency":40.76868525896414,"prefetch issued":3155,"prefetch requested":3441,"useful prefetch":795,"useless prefetch":759},"cpu0_L1I":{"LOAD":{"hit":[43630],"miss":[1033],"mshr_merge":[517]},"PREFETCH":{"hit":[1877],"miss":[4773],"mshr_merge":[142]},"RFO":{"hit":[0],"miss":[0],"mshr_merge":[0]},"TRANSLATION":{"hit":[0],"miss":[0],"mshr_merge":[0]},"WRITE":{"hit":[0],"miss":[0],"mshr_merge":[0]},"miss latency":107.32486388384756,"prefetch issued":6650,"prefetch requested":6650,"useful prefetch":4589,"useless prefetch":41},"cpu0_L2C":{"LOAD":{"hit":[9242],"miss":[2042],"mshr_merge":[80]},"PREFETCH":{"hit":[13765],"miss":[6699],"mshr_merge":[1319]},"RFO":{"hit":[890],"miss":[137],"mshr_merge":[0]},"TRANSLATION":{"hit":[3],"miss":[404],"mshr_merge":[0]},"WRITE":{"hit":[1065],"miss":[0],"mshr_merge":[0]},"miss latency":171.78104448742747,"prefetch issued":14247,"prefetch requested":14996,"useful prefetch":138,"useless prefetch":0},"cpu0_STLB":{"LOAD":{"hit":[7209],"miss":[208],"mshr_merge":[0]},"PREFETCH":{"hit":[0],"miss":[0],"mshr_merge":[0]},"RFO":{"hit":[0],"miss":[0],"mshr_merge":[0]},"TRANSLATION":{"hit":[0],"miss":[0],"mshr_merge":[0]},"WRITE":{"hit":[0],"miss":[0],"mshr_merge":[0]},"miss latency":1060.052132701422,"prefetch issued":0,"prefetch requested":0,"useful prefetch":0,"useless prefetch":0}},"traces":["/users/lijrjyan/ChampSim_checkpoint/traces/607.cactuBSSN_s-2421B.champsimtrace.xz"]}]